mkpreview/__init__.py
mkpreview/config.py
mkpreview/database.py
mkpreview/mkpreview.py
mkpreview/version.py
mkpreview-0.7.0.dist-info/AUTHORS.rst
mkpreview-0.7.0.dist-info/LICENSE
mkpreview-0.7.0.dist-info/LICENSE.rst
mkpreview-0.7.0.dist-info/METADATA
mkpreview-0.7.0.dist-info/WHEEL
mkpreview-0.7.0.dist-info/entry_points.txt
mkpreview-0.7.0.dist-info/top_level.txt
mkpreview-0.7.0.dist-info/RECORD
