Metadata-Version: 2.1
Name: mkpreview
Version: 0.7.0
Summary: mkpreview creates previews from movie files Support for all FFMPEG video types.
Home-page: https://github.com/cbitterfield/mkpreview.git
Author: Colin Bitterfield
Author-email: colin@bitterfield.com
License: MIT license
Platform: UNKNOWN
Classifier: Development Status :: 4 - Beta
Classifier: Intended Audience :: End Users/Desktop
Classifier: License :: OSI Approved :: MIT License
Classifier: Natural Language :: English
Classifier: Programming Language :: Python :: 3.5
Classifier: Programming Language :: Python :: 3.6
Classifier: Programming Language :: Python :: 3.7
Classifier: Environment :: Console
Classifier: Topic :: Multimedia :: Graphics :: Graphics Conversion
Requires-Python: >=3.5
